alibabacloud_foasconsole20190601/__init__.py
alibabacloud_foasconsole20190601/client.py
alibabacloud_foasconsole20190601/models/__init__.py
alibabacloud_foasconsole20190601/models/_change_resource_group_request.py
alibabacloud_foasconsole20190601/models/_change_resource_group_response.py
alibabacloud_foasconsole20190601/models/_change_resource_group_response_body.py
alibabacloud_foasconsole20190601/models/_convert_instance_request.py
alibabacloud_foasconsole20190601/models/_convert_instance_response.py
alibabacloud_foasconsole20190601/models/_convert_instance_response_body.py
alibabacloud_foasconsole20190601/models/_convert_prepay_instance_request.py
alibabacloud_foasconsole20190601/models/_convert_prepay_instance_response.py
alibabacloud_foasconsole20190601/models/_convert_prepay_instance_response_body.py
alibabacloud_foasconsole20190601/models/_create_instance_request.py
alibabacloud_foasconsole20190601/models/_create_instance_response.py
alibabacloud_foasconsole20190601/models/_create_instance_response_body.py
alibabacloud_foasconsole20190601/models/_create_namespace_request.py
alibabacloud_foasconsole20190601/models/_create_namespace_response.py
alibabacloud_foasconsole20190601/models/_create_namespace_response_body.py
alibabacloud_foasconsole20190601/models/_delete_instance_request.py
alibabacloud_foasconsole20190601/models/_delete_instance_response.py
alibabacloud_foasconsole20190601/models/_delete_instance_response_body.py
alibabacloud_foasconsole20190601/models/_delete_namespace_request.py
alibabacloud_foasconsole20190601/models/_delete_namespace_response.py
alibabacloud_foasconsole20190601/models/_delete_namespace_response_body.py
alibabacloud_foasconsole20190601/models/_describe_instances_request.py
alibabacloud_foasconsole20190601/models/_describe_instances_response.py
alibabacloud_foasconsole20190601/models/_describe_instances_response_body.py
alibabacloud_foasconsole20190601/models/_describe_namespaces_request.py
alibabacloud_foasconsole20190601-1.1.0.dist-info/LICENSE
alibabacloud_foasconsole20190601-1.1.0.dist-info/METADATA
alibabacloud_foasconsole20190601-1.1.0.dist-info/WHEEL
alibabacloud_foasconsole20190601-1.1.0.dist-info/top_level.txt
alibabacloud_foasconsole20190601-1.1.0.dist-info/RECORD
